aws_longer/__init__.py
aws_longer-0.4.0.dist-info/LICENSE.txt
aws_longer-0.4.0.dist-info/METADATA
aws_longer-0.4.0.dist-info/WHEEL
aws_longer-0.4.0.dist-info/entry_points.txt
aws_longer-0.4.0.dist-info/top_level.txt
aws_longer-0.4.0.dist-info/RECORD
