Metadata-Version: 2.1
Name: aws-longer
Version: 0.4.0
Summary: A program to create deterministic zip files.
Home-page: https://github.com/appfolio/aws_longer
Author: Bryce Boe
Author-email: bbzbryce@gmail.com
License: Simplified BSD License
Keywords: aws assume-role mfa session-token
Platform: UNKNOWN
Classifier: Intended Audience :: Developers
Classifier: License :: OSI Approved :: BSD License
Classifier: Programming Language :: Python :: 3.6
Classifier: Programming Language :: Python :: 3.7
Classifier: Programming Language :: Python :: 3.8
Requires-Dist: boto3
Requires-Dist: keyring
Provides-Extra: development
Requires-Dist: black ; extra == 'development'
Requires-Dist: flake8 ; extra == 'development'
Requires-Dist: pre-commit ; extra == 'development'
Requires-Dist: pytest ; extra == 'development'
Requires-Dist: twine ; extra == 'development'
Requires-Dist: wheel ; extra == 'development'
Provides-Extra: lint
Requires-Dist: black ; extra == 'lint'
Requires-Dist: flake8 ; extra == 'lint'
Provides-Extra: test
Requires-Dist: pytest ; extra == 'test'
Provides-Extra: yubikey
Requires-Dist: yubikey-manager ; extra == 'yubikey'
